lm_council/__init__.py
lm_council/analysis/__init__.py
lm_council/analysis/pairwise/__init__.py
lm_council/analysis/pairwise/affinity.py
lm_council/analysis/pairwise/agreement.py
lm_council/analysis/pairwise/bradley_terry.py
lm_council/analysis/pairwise/consistency.py
lm_council/analysis/pairwise/explicit_win_rate.py
lm_council/analysis/pairwise/length_bias.py
lm_council/analysis/pairwise/pairwise_utils.py
lm_council/analysis/pairwise/separability.py
lm_council/analysis/rubric/__init__.py
lm_council/analysis/rubric/affinity.py
lm_council/analysis/rubric/agreement.py
lm_council/analysis/visualization.py
lm_council/constants.py
lm_council/council.py
lm_council/judging/__init__.py
lm_council/judging/config.py
lm_council/judging/preset_configs/default_pairwise.yaml
lm_council/judging/preset_configs/default_rubric.yaml
lm_council/judging/prompt_builder.py
lm_council/prompts.py
lm_council/structured_outputs.py
lm_council-0.1.0.dist-info/METADATA
lm_council-0.1.0.dist-info/WHEEL
lm_council-0.1.0.dist-info/RECORD
