Metadata-Version: 2.3
Name: lm-council
Version: 0.1.0
Summary: A framework for LLM evaluation through multi-judge councils
Keywords: llm,evaluation,judging,council,machine-learning
Author: Justin Zhao
Author-email: justinxzhao@gmail.com
Requires-Python: >=3.12,<4.0
Classifier: Development Status :: 3 - Alpha
Classifier: Intended Audience :: Developers
Classifier: Intended Audience :: Science/Research
Classifier: License :: OSI Approved :: MIT License
Classifier: Operating System :: OS Independent
Classifier: Programming Language :: Python :: 3
Classifier: Programming Language :: Python :: 3.12
Classifier: Programming Language :: Python :: 3.13
Classifier: Topic :: Scientific/Engineering :: Artificial Intelligence
Classifier: Topic :: Software Development :: Libraries :: Python Modules
Requires-Dist: aiolimiter (>=1.2.1,<2.0.0)
Requires-Dist: choix (>=0.3.6,<0.4.0)
Requires-Dist: datasets (>=3.3.1,<4.0.0)
Requires-Dist: ete3[visualization] (>=3.1.3,<4.0.0)
Requires-Dist: hypothesis-jsonschema (>=0.23.1,<0.24.0)
Requires-Dist: instructor (>=1.9.0,<2.0.0)
Requires-Dist: jsonlines (>=4.0.0,<5.0.0)
Requires-Dist: nltk (>=3.9.1,<4.0.0)
Requires-Dist: openai (>=1.63.0,<2.0.0)
Requires-Dist: pyqt5 (>=5.15.11,<6.0.0)
Requires-Dist: python-dotenv (>=1.0.1,<2.0.0)
Requires-Dist: scikit-learn (>=1.6.1,<2.0.0)
Requires-Dist: seaborn (>=0.13.2,<0.14.0)
Requires-Dist: tiktoken (>=0.9.0,<0.10.0)
Requires-Dist: wordfreq (>=3.1.1,<4.0.0)
Project-URL: Homepage, https://github.com/justinzhao/llm-council-public
Project-URL: Repository, https://github.com/justinzhao/llm-council-public
